arbitros/tester2.v
module tester2 (
    output reg clk, empty , reset,
    output reg [3:0] almost_full,
    output reg [11:0] fifo_out,
    input pop,
    input [3:0] push
);

always #1 clk <= ~clk;

initial begin 
    empty = 0;
    reset = 1;
    almost_full = 0;
    fifo_out = 0;
    clk = 0;
end


initial begin
    $dumpfile("resultados.vcd");
    $dumpvars;
    repeat(2) @(posedge clk);
    reset = 0;
    fifo_out <= 12'b001010010110;
    @(posedge clk);
    fifo_out <= 12'b000110010110;
    @(posedge clk);
    fifo_out <= 12'b010000100101;
    @(posedge clk);
    fifo_out <= 12'b100000100100;
    @(posedge clk);
    fifo_out <= 12'b111010100101;
    @(posedge clk);
    almost_full[2] <= 1;
    fifo_out <= 12'b101010100101;
    repeat(5) @(posedge clk);
    $finish;
end
    
endmodule

arbitros/arbitro2.v
module arbitro2 (
    input clk, empty, reset,
    input [1:0] class,
    input [3:0] almost_full,
    output reg pop,
    output reg [3:0] push
);

//reg [1:0] selector;

always @(posedge clk)begin
    if (reset) begin
        pop <= 0; push <= 0;
    end
    
    else begin
        if (empty || |almost_full) begin 
            pop <= 0;
            push <= 0;
        end else begin
            pop <= 1;
            case (class)
                0: push <= 4'b0001;
                1: push <= 4'b0010; 
                2: push <= 4'b0100;
                3: push <= 4'b1000;
                default: push <= 4'b0000;
            endcase
        end
    end
    
end
endmodule

arbitros/testbench2.v
`timescale 1ns/1ns
`include "arbitro2.v"
`include "tester2.v"

module testebench ();

wire clk, empty, reset, pop;  
wire [3:0] almost_full, push;
wire [11:0] fifo_out;
    
arbitro2 arbiter2(/*AUTOINST*/
		  // Inputs
		  .clk			(clk),
		  .empty		(empty),
		  .reset		(reset),
          .class        (fifo_out[11:10]),
          .almost_full  (almost_full),
          // Outputs
          .pop          (pop),
          .push         (push)
          );
tester2 probador(/*AUTOINST*/
		 // Outputs
		 .clk			(clk),
		 .empty			(empty),
		 .reset			(reset),
		 .almost_full		(almost_full[3:0]),
		 .fifo_out		(fifo_out[11:0]),
		 // Inputs
		 .pop			(pop),
		 .push			(push));


endmodule

arbitros/resultados.vcd
$date
	Mon Nov 15 00:21:12 2021
$end
$version
	Icarus Verilog
$end
$timescale
	1ns
$end
$scope module testebench $end
$var wire 1 ! reset $end
$var wire 4 " push [3:0] $end
$var wire 1 # pop $end
$var wire 12 $ fifo_out [11:0] $end
$var wire 1 % empty $end
$var wire 1 & clk $end
$var wire 4 ' almost_full [3:0] $end
$scope module arbiter2 $end
$var wire 2 ( class [1:0] $end
$var wire 1 ! reset $end
$var wire 1 % empty $end
$var wire 1 & clk $end
$var wire 4 ) almost_full [3:0] $end
$var reg 1 # pop $end
$var reg 4 * push [3:0] $end
$upscope $end
$scope module probador $end
$var wire 1 # pop $end
$var wire 4 + push [3:0] $end
$var reg 4 , almost_full [3:0] $end
$var reg 1 & clk $end
$var reg 1 % empty $end
$var reg 12 - fifo_out [11:0] $end
$var reg 1 ! reset $end
$upscope $end
$upscope $end
$enddefinitions $end
#0
$dumpvars
b0 -
b0 ,
bx +
bx *
b0 )
b0 (
b0 '
0&
0%
b0 $
x#
bx "
1!
$end
#1
b0 "
b0 *
b0 +
0#
1&
#2
0&
#3
b1010010110 $
b1010010110 -
0!
1&
#4
0&
#5
b1 "
b1 *
b1 +
1#
b110010110 $
b110010110 -
1&
#6
0&
#7
b1 (
b10000100101 $
b10000100101 -
1&
#8
0&
#9
b10 (
b10 "
b10 *
b10 +
b100000100100 $
b100000100100 -
1&
#10
0&
#11
b11 (
b111010100101 $
b111010100101 -
b100 "
b100 *
b100 +
1&
#12
0&
#13
b10 (
b1000 "
b1000 *
b1000 +
b101010100101 $
b101010100101 -
b100 '
b100 )
b100 ,
1&
#14
0&
#15
b0 "
b0 *
b0 +
0#
1&
